simple_zarr_server/__init__.py
simple_zarr_server/cli.py
simple_zarr_server/server.py
simple_zarr_server-0.2.0.dist-info/METADATA
simple_zarr_server-0.2.0.dist-info/WHEEL
simple_zarr_server-0.2.0.dist-info/entry_points.txt
simple_zarr_server-0.2.0.dist-info/licenses/LICENSE
simple_zarr_server-0.2.0.dist-info/RECORD
