Metadata-Version: 2.1
Name: simple-zarr-server
Version: 0.2.0
Summary: A simple server for sharing zarr over HTTP.
Project-URL: Documentation, https://github.com/manzt/simple-zarr-server#readme
Project-URL: Issues, https://github.com/manzt/simple-zarr-server/issues
Project-URL: Source, https://github.com/manzt/simple-zarr-server
Author-email: Trevor Manz <trevor.j.manz@gmail.com>
License: BSD-3
License-File: LICENSE
Classifier: Intended Audience :: Developers
Classifier: License :: OSI Approved :: BSD License
Classifier: Operating System :: OS Independent
Requires-Python: >=3.8
Requires-Dist: numpy>=1.19.0
Requires-Dist: starlette>=0.13.6
Requires-Dist: uvicorn>=0.11.6
Requires-Dist: zarr>=2.4.0
